{"id":"10175601944","name":"Gründerhub frankfurt.rhein.main Kick-Off Event","takenAt":"2013-10-09T13:43:30.000Z","rotation":0,"license":"Attribution-NoDerivs License","geo":{"lat":50.113341,"lng":8.66793},"tags":["ghfrm","startup","frankfurtrheinmain","GründerhubFrankfurtRheinMain"],"url":"//images.ctfassets.net/bncv3c2gt878/2W74dc9HqF5ZGNLYrEJxun/d8ce97a21f51dfc86c5ab4556be2bd6f/grnderhub-frankfurtrheinmain-kick-off-event_10175601944_o","size":925669,"image":{"width":2592,"height":1944},"contentType":"image/jpeg"}