{"id":"9096968209","name":"Sturmschäden 21. Juni 2013 im Friedrichsring Offenbach","takenAt":"2013-06-21T06:05:57.000Z","rotation":0,"license":"Attribution-NoDerivs License","geo":{"lat":50.094382,"lng":8.764042},"tags":["Offenbach","Unwetter","Sturm","Wasser","Überschwemmung"],"url":"//images.ctfassets.net/bncv3c2gt878/7k6ECSMzuq8NBJohJ0RjUy/00eb7e1b9c83e6c7cece0429bef62502/sturmschden-21-juni-2013-im-friedrichsring-offenbach_9096968209_o","size":1098044,"image":{"width":1944,"height":2592},"contentType":"image/jpeg"}